asiocmd/__init__.py
asiocmd/async_cmd.py
asiocmd/cmd.py
asiocmd/decorators.py
asiocmd/typing.py
asiocmd-1.0.0.dist-info/licenses/LICENSE
asiocmd-1.0.0.dist-info/METADATA
asiocmd-1.0.0.dist-info/WHEEL
asiocmd-1.0.0.dist-info/top_level.txt
asiocmd-1.0.0.dist-info/RECORD
