Metadata-Version: 2.4
Name: asiocmd
Version: 1.0.0
Summary: Modern and asynchronous support for cmd.Cmd
Author-email: Parth Acharya <parthacharya@protonmail.com>
License:  The MIT License (MIT)
Project-URL: Repository, https://github.com/parthacharyaaaaa/async_cmd
Project-URL: Download, https://github.com/parthacharyaaaaa/async_cmd/archive/refs/heads/main.zip
Keywords: asiocmd,async,tool,cmd,cli
Classifier: License :: OSI Approved :: MIT License
Classifier: Programming Language :: Python :: 3
Classifier: Programming Language :: Python :: 3.10
Classifier: Programming Language :: Python :: 3.11
Classifier: Programming Language :: Python :: 3.12
Classifier: Programming Language :: Python :: 3.13
Classifier: Intended Audience :: Developers
Classifier: Topic :: Software Development :: Libraries
Requires-Python: >=3.10
License-File: LICENSE
Provides-Extra: dev
Requires-Dist: pytest>=9.0.0; extra == "dev"
Requires-Dist: pytest-asyncio>=1.3.0; extra == "dev"
Requires-Dist: pytest-mock>=3.15.1; extra == "dev"
Dynamic: license-file
